aqueduct/__init__.py
aqueduct/version.py
aqueduct/core/__init__.py
aqueduct/core/aq.py
aqueduct/core/input.py
aqueduct/core/logging.py
aqueduct/core/pid.py
aqueduct/core/prompt.py
aqueduct/core/recordable.py
aqueduct/core/setpoint.py
aqueduct/core/socket_constants.py
aqueduct/core/units.py
aqueduct/core/utils.py
aqueduct/devices/__init__.py
aqueduct/devices/balance/__init__.py
aqueduct/devices/base/__init__.py
aqueduct/devices/base/obj.py
aqueduct/devices/base/utils.py
aqueduct/devices/mass_flow/__init__.py
aqueduct/devices/mass_flow/meter.py
aqueduct/devices/optical_density/__init__.py
aqueduct/devices/ph/__init__.py
aqueduct/devices/pressure/__init__.py
aqueduct/devices/pressure/transducer.py
aqueduct/devices/pump/__init__.py
aqueduct/devices/pump/peristaltic/__init__.py
aqueduct/devices/pump/peristaltic/types/__init__.py
aqueduct/devices/pump/peristaltic/types/aqueduct.py
aqueduct/devices/pump/peristaltic/types/masterflex.py
aqueduct/devices/pump/syringe/__init__.py
aqueduct/devices/pump/syringe/types/__init__.py
aqueduct/devices/pump/syringe/types/tricontinent.py
aqueduct/devices/temperature/__init__.py
aqueduct/devices/test_device/__init__.py
aqueduct/devices/valve/__init__.py
aqueduct/devices/valve/pinch.py
aqueduct/devices/valve/solenoid.py
aqueduct/tests/__init__.py
aqueduct/tests/test_imports.py
aqueduct/tests/core/__init__.py
aqueduct/tests/core/test_init_params.py
aqueduct/tests/core/test_pid.py
aqueduct/tests/core/test_units.py
aqueduct/tests/core/test_utils.py
aqueduct/tests/devices/__init__.py
aqueduct/tests/devices/test_utils.py
aqueduct/tests/devices/pump/__init__.py
aqueduct/tests/devices/pump/test_peristaltic.py
aqueduct/tests/devices/pump/test_syringe.py
aqueduct_py-0.0.10.dist-info/METADATA
aqueduct_py-0.0.10.dist-info/WHEEL
aqueduct_py-0.0.10.dist-info/top_level.txt
aqueduct_py-0.0.10.dist-info/zip-safe
aqueduct_py-0.0.10.dist-info/RECORD
