Metadata-Version: 2.1
Name: aqueduct-py
Version: 0.0.10
Summary: Aqueduct Core package.
Home-page: http://packages.python.org/*
Author: Aqueduct Fluidics, LLC
Author-email: info@aqueductfluidics.com
License: BSD
Classifier: Development Status :: 3 - Alpha
Classifier: License :: OSI Approved :: BSD License
Classifier: Operating System :: OS Independent
Classifier: Topic :: Scientific/Engineering
Requires-Python: >=3.7.1
Requires-Dist: psutil
Provides-Extra: test
Requires-Dist: black ~=21.6b0 ; extra == 'test'
Requires-Dist: pytest ==6.* ; extra == 'test'
